[
  {
    "arguments": [
      "/usr/bin/g++",
      "-fdiagnostics-color=always",
      "-g3",
      "-std=c2x",
      "-Wno-missing-field-initializers",
      "-Wno-unknown-pragmas",
      "-Wall",
      "-Wconversion",
      "-Wshadow",
      "-Wextra",
      "-fanalyzer",
      "-fsanitize=address",
      "-fsanitize=leak",
      "-Iinclude",
      "-Iext",
      "-I../common/include",
      "-I/usr/local/include",
      "-c",
      "-o",
      "obj/debug/srcuser.o",
      "src/user.c"
    ],
    "directory": "/home/leonard/workspace/cpp/PSC/server",
    "file": "/home/leonard/workspace/cpp/PSC/server/src/user.c",
    "output": "/home/leonard/workspace/cpp/PSC/server/obj/debug/srcuser.o"
  },
  {
    "arguments": [
      "/usr/bin/g++",
      "-fdiagnostics-color=always",
      "-g3",
      "-std=c2x",
      "-Wno-missing-field-initializers",
      "-Wno-unknown-pragmas",
      "-Wall",
      "-Wconversion",
      "-Wshadow",
      "-Wextra",
      "-fanalyzer",
      "-fsanitize=address",
      "-fsanitize=leak",
      "-Iinclude",
      "-Iext",
      "-I../common/include",
      "-I/usr/local/include",
      "-c",
      "-o",
      "obj/debug/srcserver.o",
      "src/server.c"
    ],
    "directory": "/home/leonard/workspace/cpp/PSC/server",
    "file": "/home/leonard/workspace/cpp/PSC/server/src/server.c",
    "output": "/home/leonard/workspace/cpp/PSC/server/obj/debug/srcserver.o"
  },
  {
    "arguments": [
      "/usr/bin/g++",
      "-fdiagnostics-color=always",
      "-g3",
      "-std=c2x",
      "-Wno-missing-field-initializers",
      "-Wno-unknown-pragmas",
      "-Wall",
      "-Wconversion",
      "-Wshadow",
      "-Wextra",
      "-fanalyzer",
      "-fsanitize=address",
      "-fsanitize=leak",
      "-Iinclude",
      "-Iext",
      "-I../common/include",
      "-I/usr/local/include",
      "-c",
      "-o",
      "obj/debug/..commonsrcminiVector.o",
      "../common/src/miniVector.cpp"
    ],
    "directory": "/home/leonard/workspace/cpp/PSC/server",
    "file": "/home/leonard/workspace/cpp/PSC/common/src/miniVector.cpp",
    "output": "/home/leonard/workspace/cpp/PSC/server/obj/debug/..commonsrcminiVector.o"
  },
  {
    "arguments": [
      "/usr/bin/g++",
      "-fdiagnostics-color=always",
      "-g3",
      "-std=c2x",
      "-Wno-missing-field-initializers",
      "-Wno-unknown-pragmas",
      "-Wall",
      "-Wconversion",
      "-Wshadow",
      "-Wextra",
      "-fanalyzer",
      "-fsanitize=address",
      "-fsanitize=leak",
      "-Iinclude",
      "-Iext",
      "-I../common/include",
      "-I/usr/local/include",
      "-c",
      "-o",
      "obj/debug/..commonsrcutils.o",
      "../common/src/utils.cpp"
    ],
    "directory": "/home/leonard/workspace/cpp/PSC/server",
    "file": "/home/leonard/workspace/cpp/PSC/common/src/utils.cpp",
    "output": "/home/leonard/workspace/cpp/PSC/server/obj/debug/..commonsrcutils.o"
  },
  {
    "arguments": [
      "/usr/bin/g++",
      "-fdiagnostics-color=always",
      "-g3",
      "-std=c2x",
      "-Wno-missing-field-initializers",
      "-Wno-unknown-pragmas",
      "-Wall",
      "-Wconversion",
      "-Wshadow",
      "-Wextra",
      "-fanalyzer",
      "-fsanitize=address",
      "-fsanitize=leak",
      "-Iinclude",
      "-Iext",
      "-I../common/include",
      "-I/usr/local/include",
      "-c",
      "-o",
      "obj/debug/..commonsrcheader.o",
      "../common/src/header.cpp"
    ],
    "directory": "/home/leonard/workspace/cpp/PSC/server",
    "file": "/home/leonard/workspace/cpp/PSC/common/src/header.cpp",
    "output": "/home/leonard/workspace/cpp/PSC/server/obj/debug/..commonsrcheader.o"
  },
  {
    "arguments": [
      "/usr/bin/g++",
      "-fdiagnostics-color=always",
      "-g3",
      "-std=c2x",
      "-Wno-missing-field-initializers",
      "-Wno-unknown-pragmas",
      "-Wall",
      "-Wconversion",
      "-Wshadow",
      "-Wextra",
      "-fanalyzer",
      "-fsanitize=address",
      "-fsanitize=leak",
      "-Iinclude",
      "-Iext",
      "-I../common/include",
      "-I/usr/local/include",
      "-c",
      "-o",
      "obj/debug/..commonsrclogger.o",
      "../common/src/logger.cpp"
    ],
    "directory": "/home/leonard/workspace/cpp/PSC/server",
    "file": "/home/leonard/workspace/cpp/PSC/common/src/logger.cpp",
    "output": "/home/leonard/workspace/cpp/PSC/server/obj/debug/..commonsrclogger.o"
  }
]
